[
    {
        "Real score": {
            "Dice": 0.0,
            "Hausdorff": 168.0,
            "ASSD": 93.41517025380955
        },
        "RCA score": {
            "Dice": 0.0030211480362537764,
            "Hausdorff": 70.60453243241541,
            "ASSD": 32.55455819944178
        }
    },
    {
        "Real score": {
            "Dice": 0.8587742672249714,
            "Hausdorff": 121.01652779682617,
            "ASSD": 2.8862138513245865
        },
        "RCA score": {
            "Dice": 0.7102164830991264,
            "Hausdorff": 80.52949770115296,
            "ASSD": 2.1722827115429295
        }
    },
    {
        "Real score": {
            "Dice": 0.6205041662271912,
            "Hausdorff": 126.75172582651489,
            "ASSD": 8.073871702802432
        },
        "RCA score": {
            "Dice": 0.3954510993176649,
            "Hausdorff": 92.19544457292888,
            "ASSD": 4.095230774765737
        }
    },
    {
        "Real score": {
            "Dice": 0.25949184766952815,
            "Hausdorff": 127.58134659894448,
            "ASSD": 17.681751708764093
        },
        "RCA score": {
            "Dice": 0.2181967213114754,
            "Hausdorff": 101.25709851659784,
            "ASSD": 10.083552372985096
        }
    },
    {
        "Real score": {
            "Dice": 0.0,
            "Hausdorff": 152.2694979304785,
            "ASSD": 97.09130482795796
        },
        "RCA score": {
            "Dice": 0.016761448668063453,
            "Hausdorff": 67.11929677819934,
            "ASSD": 28.353850307802663
        }
    },
    {
        "Real score": {
            "Dice": 0.5697752058758068,
            "Hausdorff": 152.2694979304785,
            "ASSD": 22.70299076649382
        },
        "RCA score": {
            "Dice": 0.5157164535009755,
            "Hausdorff": 105.47511554864494,
            "ASSD": 7.34701384888737
        }
    },
    {
        "Real score": {
            "Dice": 0.6031503579952268,
            "Hausdorff": 153.05227865013967,
            "ASSD": 28.6341065590878
        },
        "RCA score": {
            "Dice": 0.559854434016472,
            "Hausdorff": 121.51131634543344,
            "ASSD": 9.465805427515955
        }
    },
    {
        "Real score": {
            "Dice": 0.6234203875315922,
            "Hausdorff": 153.05227865013967,
            "ASSD": 26.67154305791044
        },
        "RCA score": {
            "Dice": 0.6043670098427424,
            "Hausdorff": 110.38568747804219,
            "ASSD": 9.077921567464156
        }
    },
    {
        "Real score": {
            "Dice": 0.7321214358217218,
            "Hausdorff": 152.43359209832983,
            "ASSD": 21.02738088765179
        },
        "RCA score": {
            "Dice": 0.7256009748532182,
            "Hausdorff": 106.40018796975878,
            "ASSD": 5.71464398761541
        }
    },
    {
        "Real score": {
            "Dice": 0.7837561564910325,
            "Hausdorff": 152.43359209832983,
            "ASSD": 17.004350629808748
        },
        "RCA score": {
            "Dice": 0.7325961032122169,
            "Hausdorff": 105.19030373565806,
            "ASSD": 5.672871755859536
        }
    },
    {
        "Real score": {
            "Dice": 0.8086615643083815,
            "Hausdorff": 151.81897114655993,
            "ASSD": 13.296763906847785
        },
        "RCA score": {
            "Dice": 0.7309794031105507,
            "Hausdorff": 105.68348972285122,
            "ASSD": 3.7965263327048584
        }
    },
    {
        "Real score": {
            "Dice": 0.15941140404659718,
            "Hausdorff": 136.4587849865299,
            "ASSD": 13.584245016603605
        },
        "RCA score": {
            "Dice": 0.19598513011152416,
            "Hausdorff": 70.22819946431775,
            "ASSD": 13.214705232302677
        }
    },
    {
        "Real score": {
            "Dice": 0.712061127768643,
            "Hausdorff": 169.85287751463028,
            "ASSD": 22.347850338766964
        },
        "RCA score": {
            "Dice": 0.6416518184676658,
            "Hausdorff": 89.47066558375433,
            "ASSD": 5.332156650960514
        }
    },
    {
        "Real score": {
            "Dice": 0.14542000271407246,
            "Hausdorff": 62.22539674441618,
            "ASSD": 16.848652684616212
        },
        "RCA score": {
            "Dice": 0.1674774774774775,
            "Hausdorff": 58.66856057549052,
            "ASSD": 9.833578630902275
        }
    },
    {
        "Real score": {
            "Dice": 0.9011914640447152,
            "Hausdorff": 92.9569792968769,
            "ASSD": 0.7659107653333701
        },
        "RCA score": {
            "Dice": 0.6850751107748838,
            "Hausdorff": 70.03570517957252,
            "ASSD": 1.8948913454644407
        }
    },
    {
        "Real score": {
            "Dice": 0.9675674894084646,
            "Hausdorff": 93.60555539069249,
            "ASSD": 0.3287361459709823
        },
        "RCA score": {
            "Dice": 0.814232413649538,
            "Hausdorff": 50.53711507397311,
            "ASSD": 1.6779966543087201
        }
    },
    {
        "Real score": {
            "Dice": 0.0,
            "Hausdorff": 158.79546593023366,
            "ASSD": 114.47870509512207
        },
        "RCA score": {
            "Dice": 0.016415868673050615,
            "Hausdorff": 53.600373133029585,
            "ASSD": 23.42307355042381
        }
    },
    {
        "Real score": {
            "Dice": 0.5374449339207048,
            "Hausdorff": 159.45218719101973,
            "ASSD": 33.450683619413525
        },
        "RCA score": {
            "Dice": 0.46994535519125685,
            "Hausdorff": 104.00480758118829,
            "ASSD": 14.397421345382446
        }
    },
    {
        "Real score": {
            "Dice": 0.0008265145879824779,
            "Hausdorff": 118.92854997854805,
            "ASSD": 39.107378661315586
        },
        "RCA score": {
            "Dice": 0.034132705605414156,
            "Hausdorff": 63.56886030125127,
            "ASSD": 24.48442318638884
        }
    },
    {
        "Real score": {
            "Dice": 0.9009091955345839,
            "Hausdorff": 119.50313803411188,
            "ASSD": 1.6121989771002858
        },
        "RCA score": {
            "Dice": 0.819672131147541,
            "Hausdorff": 55.569775957799216,
            "ASSD": 1.0803271771902438
        }
    },
    {
        "Real score": {
            "Dice": 0.7593347688642507,
            "Hausdorff": 118.92854997854805,
            "ASSD": 7.018363387358375
        },
        "RCA score": {
            "Dice": 0.7957856769968202,
            "Hausdorff": 91.67878707749138,
            "ASSD": 1.8954507716926716
        }
    },
    {
        "Real score": {
            "Dice": 0.7716334931884734,
            "Hausdorff": 119.60351165413162,
            "ASSD": 9.54834394166999
        },
        "RCA score": {
            "Dice": 0.7802611402815854,
            "Hausdorff": 103.9471019317037,
            "ASSD": 3.6597426567727256
        }
    },
    {
        "Real score": {
            "Dice": 0.0,
            "Hausdorff": 135.0,
            "ASSD": 83.99605873729354
        },
        "RCA score": {
            "Dice": 0.002657218777679362,
            "Hausdorff": 72.20110802473879,
            "ASSD": 28.062686338953604
        }
    },
    {
        "Real score": {
            "Dice": 0.30026175800050664,
            "Hausdorff": 146.102703602637,
            "ASSD": 27.73384834444265
        },
        "RCA score": {
            "Dice": 0.287292817679558,
            "Hausdorff": 97.16995420396162,
            "ASSD": 12.397747988256508
        }
    },
    {
        "Real score": {
            "Dice": 0.5560313007529898,
            "Hausdorff": 145.34441853748632,
            "ASSD": 20.895271999345113
        },
        "RCA score": {
            "Dice": 0.5328550464699169,
            "Hausdorff": 99.02019995940222,
            "ASSD": 5.647328643708227
        }
    },
    {
        "Real score": {
            "Dice": 0.6244439737343783,
            "Hausdorff": 143.83671297690307,
            "ASSD": 18.637738775840138
        },
        "RCA score": {
            "Dice": 0.5459657892681403,
            "Hausdorff": 98.4733466477097,
            "ASSD": 6.8354008310173375
        }
    },
    {
        "Real score": {
            "Dice": 0.8808214640609473,
            "Hausdorff": 132.7742444904131,
            "ASSD": 5.9086477917109805
        },
        "RCA score": {
            "Dice": 0.7043263077054356,
            "Hausdorff": 88.05679985100527,
            "ASSD": 3.5864525972606285
        }
    },
    {
        "Real score": {
            "Dice": 0.414468280823943,
            "Hausdorff": 126.49110640673517,
            "ASSD": 4.801645569311944
        },
        "RCA score": {
            "Dice": 0.3468245599805337,
            "Hausdorff": 31.016124838541646,
            "ASSD": 3.889544612669556
        }
    },
    {
        "Real score": {
            "Dice": 0.9114735115314099,
            "Hausdorff": 126.24579200908045,
            "ASSD": 2.5803006115178
        },
        "RCA score": {
            "Dice": 0.8092109943794911,
            "Hausdorff": 89.47066558375433,
            "ASSD": 2.1293332222393744
        }
    },
    {
        "Real score": {
            "Dice": 0.9469857618903362,
            "Hausdorff": 94.04786015641186,
            "ASSD": 0.3928726517473955
        },
        "RCA score": {
            "Dice": 0.7606185785404088,
            "Hausdorff": 56.79788728465171,
            "ASSD": 1.6558717143570345
        }
    },
    {
        "Real score": {
            "Dice": 0.9336633225792195,
            "Hausdorff": 94.04786015641186,
            "ASSD": 0.5689525407846445
        },
        "RCA score": {
            "Dice": 0.7500200325863404,
            "Hausdorff": 64.77653896280658,
            "ASSD": 1.6285729409608871
        }
    },
    {
        "Real score": {
            "Dice": 0.054649691013327374,
            "Hausdorff": 127.01574705523721,
            "ASSD": 12.13811813501149
        },
        "RCA score": {
            "Dice": 0.1700532978014657,
            "Hausdorff": 41.182520563948,
            "ASSD": 9.362924138179311
        }
    },
    {
        "Real score": {
            "Dice": 0.6681884326761206,
            "Hausdorff": 152.22680447279973,
            "ASSD": 6.080762186249524
        },
        "RCA score": {
            "Dice": 0.6213664365538805,
            "Hausdorff": 48.507731342539614,
            "ASSD": 3.449443033270955
        }
    },
    {
        "Real score": {
            "Dice": 0.6564123166987115,
            "Hausdorff": 152.22680447279973,
            "ASSD": 11.272701227059896
        },
        "RCA score": {
            "Dice": 0.637780431094074,
            "Hausdorff": 55.94640292279746,
            "ASSD": 3.407141867125437
        }
    },
    {
        "Real score": {
            "Dice": 0.10386106895970325,
            "Hausdorff": 130.23056476879765,
            "ASSD": 7.795221542774791
        },
        "RCA score": {
            "Dice": 0.1221826809015421,
            "Hausdorff": 36.6742416417845,
            "ASSD": 6.178605942935972
        }
    },
    {
        "Real score": {
            "Dice": 0.8636686390532544,
            "Hausdorff": 129.634100452003,
            "ASSD": 6.187435531573726
        },
        "RCA score": {
            "Dice": 0.7877412031782066,
            "Hausdorff": 89.30845424706443,
            "ASSD": 2.342577942113058
        }
    },
    {
        "Real score": {
            "Dice": 0.5610351044649485,
            "Hausdorff": 108.4665847162157,
            "ASSD": 4.2163212904163965
        },
        "RCA score": {
            "Dice": 0.5868231528407576,
            "Hausdorff": 19.6468827043885,
            "ASSD": 2.011770368294611
        }
    },
    {
        "Real score": {
            "Dice": 0.9209351011863224,
            "Hausdorff": 151.4859729479928,
            "ASSD": 1.2131798990737928
        },
        "RCA score": {
            "Dice": 0.617637487796941,
            "Hausdorff": 62.609903369994115,
            "ASSD": 5.369302989380888
        }
    },
    {
        "Real score": {
            "Dice": 0.39104268719384183,
            "Hausdorff": 130.6981254647518,
            "ASSD": 7.630855396609928
        },
        "RCA score": {
            "Dice": 0.2739356178608515,
            "Hausdorff": 70.178344238091,
            "ASSD": 10.031656681218767
        }
    },
    {
        "Real score": {
            "Dice": 0.5563253784962792,
            "Hausdorff": 147.29901561110313,
            "ASSD": 25.489101384119486
        },
        "RCA score": {
            "Dice": 0.4797494559159191,
            "Hausdorff": 41.43669871020132,
            "ASSD": 6.011552735688777
        }
    },
    {
        "Real score": {
            "Dice": 0.5564729458917835,
            "Hausdorff": 158.83639381451596,
            "ASSD": 27.758715731198723
        },
        "RCA score": {
            "Dice": 0.42621468926553674,
            "Hausdorff": 58.240879114244144,
            "ASSD": 13.084763864799706
        }
    },
    {
        "Real score": {
            "Dice": 0.6165342189538607,
            "Hausdorff": 157.74663229368798,
            "ASSD": 32.31677423308612
        },
        "RCA score": {
            "Dice": 0.4587341170882318,
            "Hausdorff": 55.94640292279746,
            "ASSD": 8.806983795924635
        }
    },
    {
        "Real score": {
            "Dice": 0.5761440360090022,
            "Hausdorff": 147.29901561110313,
            "ASSD": 29.83917761540297
        },
        "RCA score": {
            "Dice": 0.49042455006922014,
            "Hausdorff": 55.47071299343465,
            "ASSD": 6.225095263576904
        }
    },
    {
        "Real score": {
            "Dice": 0.5724592611021271,
            "Hausdorff": 132.2800060477773,
            "ASSD": 5.886307931571425
        },
        "RCA score": {
            "Dice": 0.320846488608243,
            "Hausdorff": 65.29931086925804,
            "ASSD": 9.640232903759472
        }
    },
    {
        "Real score": {
            "Dice": 0.27415913016969823,
            "Hausdorff": 140.85808461000738,
            "ASSD": 35.42929368481075
        },
        "RCA score": {
            "Dice": 0.6238100197896053,
            "Hausdorff": 67.80117993073571,
            "ASSD": 3.906034590397685
        }
    },
    {
        "Real score": {
            "Dice": 0.5889494549058474,
            "Hausdorff": 149.77316181479245,
            "ASSD": 31.954398449451126
        },
        "RCA score": {
            "Dice": 0.5655994592269403,
            "Hausdorff": 78.64477096412705,
            "ASSD": 7.301710127542694
        }
    },
    {
        "Real score": {
            "Dice": 0.5116798601330679,
            "Hausdorff": 150.90394295710104,
            "ASSD": 37.40007125908088
        },
        "RCA score": {
            "Dice": 0.5570312073017435,
            "Hausdorff": 94.81033698917012,
            "ASSD": 8.008967392453643
        }
    },
    {
        "Real score": {
            "Dice": 0.3819500973279066,
            "Hausdorff": 150.90394295710104,
            "ASSD": 37.77025998161402
        },
        "RCA score": {
            "Dice": 0.5891495388190864,
            "Hausdorff": 77.23341245859851,
            "ASSD": 5.911587426275904
        }
    },
    {
        "Real score": {
            "Dice": 0.3114843998037348,
            "Hausdorff": 150.08331019803634,
            "ASSD": 37.63688996747127
        },
        "RCA score": {
            "Dice": 0.61008042551828,
            "Hausdorff": 77.23341245859851,
            "ASSD": 4.631747582798664
        }
    },
    {
        "Real score": {
            "Dice": 0.2762221653442539,
            "Hausdorff": 148.44864431849825,
            "ASSD": 37.056226631240534
        },
        "RCA score": {
            "Dice": 0.6022770733429437,
            "Hausdorff": 77.23341245859851,
            "ASSD": 4.544544136087656
        }
    },
    {
        "Real score": {
            "Dice": 0.270489748859592,
            "Hausdorff": 140.85808461000738,
            "ASSD": 37.01726205751382
        },
        "RCA score": {
            "Dice": 0.5879358345485881,
            "Hausdorff": 77.93587107359485,
            "ASSD": 4.317989302928362
        }
    },
    {
        "Real score": {
            "Dice": 0.26304628659175666,
            "Hausdorff": 140.85808461000738,
            "ASSD": 36.86809568082048
        },
        "RCA score": {
            "Dice": 0.6031842304776346,
            "Hausdorff": 77.23341245859851,
            "ASSD": 3.515208399997812
        }
    },
    {
        "Real score": {
            "Dice": 0.27475940730179743,
            "Hausdorff": 140.85808461000738,
            "ASSD": 36.02018788815806
        },
        "RCA score": {
            "Dice": 0.6119343211854225,
            "Hausdorff": 70.00714249274856,
            "ASSD": 4.219149907894829
        }
    },
    {
        "Real score": {
            "Dice": 0.00014923145799134458,
            "Hausdorff": 191.84629264074925,
            "ASSD": 90.84093574228453
        },
        "RCA score": {
            "Dice": 0.014724786724319271,
            "Hausdorff": 62.369864518050704,
            "ASSD": 23.407454151666993
        }
    },
    {
        "Real score": {
            "Dice": 0.7876565474401362,
            "Hausdorff": 122.0245876862528,
            "ASSD": 4.0361950851705535
        },
        "RCA score": {
            "Dice": 0.6704119850187266,
            "Hausdorff": 99.29753269845128,
            "ASSD": 3.154550535969183
        }
    },
    {
        "Real score": {
            "Dice": 0.9570686863799617,
            "Hausdorff": 122.67436570041843,
            "ASSD": 0.544278890220942
        },
        "RCA score": {
            "Dice": 0.7000771406531242,
            "Hausdorff": 57.28001396647874,
            "ASSD": 2.9360388583869685
        }
    },
    {
        "Real score": {
            "Dice": 0.9549714371056267,
            "Hausdorff": 122.67436570041843,
            "ASSD": 0.4271986010031866
        },
        "RCA score": {
            "Dice": 0.6883154084529048,
            "Hausdorff": 57.584720195551874,
            "ASSD": 3.0594253209340074
        }
    },
    {
        "Real score": {
            "Dice": 0.042864993588569336,
            "Hausdorff": 135.20355024924456,
            "ASSD": 17.44802064093705
        },
        "RCA score": {
            "Dice": 0.08016946390744664,
            "Hausdorff": 78.24321056807422,
            "ASSD": 24.928765930394984
        }
    },
    {
        "Real score": {
            "Dice": 0.5036335429084674,
            "Hausdorff": 179.6941846582688,
            "ASSD": 36.191119626196944
        },
        "RCA score": {
            "Dice": 0.38883174136664217,
            "Hausdorff": 118.82760622010359,
            "ASSD": 16.08864306578095
        }
    },
    {
        "Real score": {
            "Dice": 0.5890017839137517,
            "Hausdorff": 180.42449944505873,
            "ASSD": 33.60991065645749
        },
        "RCA score": {
            "Dice": 0.4613793103448276,
            "Hausdorff": 104.20172743289815,
            "ASSD": 15.146046679306766
        }
    },
    {
        "Real score": {
            "Dice": 0.6579995491094912,
            "Hausdorff": 180.42449944505873,
            "ASSD": 31.193784966658168
        },
        "RCA score": {
            "Dice": 0.5031771247021446,
            "Hausdorff": 103.22790320451152,
            "ASSD": 13.806277270845658
        }
    },
    {
        "Real score": {
            "Dice": 0.689649981181784,
            "Hausdorff": 180.42449944505873,
            "ASSD": 28.493154210331216
        },
        "RCA score": {
            "Dice": 0.5165209265069087,
            "Hausdorff": 103.22790320451152,
            "ASSD": 12.061485426414876
        }
    },
    {
        "Real score": {
            "Dice": 0.0,
            "Hausdorff": 159.76545308670458,
            "ASSD": 102.53009194691496
        },
        "RCA score": {
            "Dice": 0.000615447738229562,
            "Hausdorff": 155.9134375222354,
            "ASSD": 72.84129818636188
        }
    },
    {
        "Real score": {
            "Dice": 0.9377431906614786,
            "Hausdorff": 138.70832707519762,
            "ASSD": 1.3313696733035245
        },
        "RCA score": {
            "Dice": 0.7826013655904914,
            "Hausdorff": 56.08029957123981,
            "ASSD": 1.963958224364615
        }
    },
    {
        "Real score": {
            "Dice": 0.19250059708621925,
            "Hausdorff": 149.80654191322887,
            "ASSD": 21.97569866357183
        },
        "RCA score": {
            "Dice": 0.3186874304783092,
            "Hausdorff": 79.22752047110903,
            "ASSD": 8.76611818174617
        }
    },
    {
        "Real score": {
            "Dice": 0.6625036475051065,
            "Hausdorff": 149.164338901763,
            "ASSD": 12.162009367134859
        },
        "RCA score": {
            "Dice": 0.7733755942947702,
            "Hausdorff": 79.07591289387686,
            "ASSD": 2.3105559459333143
        }
    },
    {
        "Real score": {
            "Dice": 0.0,
            "Hausdorff": 223.0,
            "ASSD": 125.06397428211258
        },
        "RCA score": {
            "Dice": 0.010563718428886969,
            "Hausdorff": 101.59724405711013,
            "ASSD": 40.691587521482326
        }
    },
    {
        "Real score": {
            "Dice": 0.05776986330068611,
            "Hausdorff": 88.81441324469807,
            "ASSD": 19.511424373559493
        },
        "RCA score": {
            "Dice": 0.17166118136151048,
            "Hausdorff": 58.249463516842795,
            "ASSD": 11.306520515243083
        }
    },
    {
        "Real score": {
            "Dice": 0.3739989554317549,
            "Hausdorff": 88.95504482602435,
            "ASSD": 12.227949270499185
        },
        "RCA score": {
            "Dice": 0.3112130164469333,
            "Hausdorff": 49.040799340956916,
            "ASSD": 7.077623706233085
        }
    },
    {
        "Real score": {
            "Dice": 0.3496522027161312,
            "Hausdorff": 88.95504482602435,
            "ASSD": 11.404641572560875
        },
        "RCA score": {
            "Dice": 0.25972159856308935,
            "Hausdorff": 60.876925020897694,
            "ASSD": 7.708953537358368
        }
    },
    {
        "Real score": {
            "Dice": 0.37181978798586574,
            "Hausdorff": 88.95504482602435,
            "ASSD": 9.09714154618257
        },
        "RCA score": {
            "Dice": 0.2840454964648017,
            "Hausdorff": 61.465437442517235,
            "ASSD": 6.265161651861161
        }
    },
    {
        "Real score": {
            "Dice": 0.4450969128316419,
            "Hausdorff": 87.96590248499699,
            "ASSD": 8.704564269377753
        },
        "RCA score": {
            "Dice": 0.4272267079446095,
            "Hausdorff": 50.59644256269407,
            "ASSD": 4.10943479272926
        }
    },
    {
        "Real score": {
            "Dice": 0.4377125986778769,
            "Hausdorff": 86.97700845625813,
            "ASSD": 7.81529028000135
        },
        "RCA score": {
            "Dice": 0.45078016501919776,
            "Hausdorff": 47.41307836451879,
            "ASSD": 4.3302978100163445
        }
    },
    {
        "Real score": {
            "Dice": 7.016312927556569e-05,
            "Hausdorff": 152.16109883935513,
            "ASSD": 74.03885017286684
        },
        "RCA score": {
            "Dice": 0.009386169386169386,
            "Hausdorff": 121.37956994486346,
            "ASSD": 40.375533530336924
        }
    },
    {
        "Real score": {
            "Dice": 0.1663690025730286,
            "Hausdorff": 113.59577456930342,
            "ASSD": 12.930177618223075
        },
        "RCA score": {
            "Dice": 0.15977539561000512,
            "Hausdorff": 51.42956348249516,
            "ASSD": 11.396767708212533
        }
    },
    {
        "Real score": {
            "Dice": 0.2500923846613036,
            "Hausdorff": 114.49454135459908,
            "ASSD": 11.087439849209447
        },
        "RCA score": {
            "Dice": 0.15817442950922164,
            "Hausdorff": 51.62363799656123,
            "ASSD": 10.192259142341278
        }
    },
    {
        "Real score": {
            "Dice": 0.260825267447784,
            "Hausdorff": 114.93476410555685,
            "ASSD": 12.210223893271863
        },
        "RCA score": {
            "Dice": 0.2126740635937151,
            "Hausdorff": 55.036351623268054,
            "ASSD": 9.73265541000323
        }
    },
    {
        "Real score": {
            "Dice": 0.32797179684917926,
            "Hausdorff": 114.93476410555685,
            "ASSD": 10.406330333347146
        },
        "RCA score": {
            "Dice": 0.2778354336545589,
            "Hausdorff": 51.31276644267,
            "ASSD": 9.098045525493447
        }
    },
    {
        "Real score": {
            "Dice": 0.4363522863236748,
            "Hausdorff": 114.93476410555685,
            "ASSD": 7.7729353534885
        },
        "RCA score": {
            "Dice": 0.41964518653795985,
            "Hausdorff": 53.71219600798314,
            "ASSD": 6.821851499718018
        }
    },
    {
        "Real score": {
            "Dice": 0.47076023391812866,
            "Hausdorff": 114.93476410555685,
            "ASSD": 7.511535643601567
        },
        "RCA score": {
            "Dice": 0.4741581832419734,
            "Hausdorff": 50.08991914547278,
            "ASSD": 7.2023818330000635
        }
    },
    {
        "Real score": {
            "Dice": 0.3246581050876994,
            "Hausdorff": 95.01578816175763,
            "ASSD": 7.851252251012442
        },
        "RCA score": {
            "Dice": 0.3153558052434457,
            "Hausdorff": 49.03060268852505,
            "ASSD": 6.867528358019798
        }
    },
    {
        "Real score": {
            "Dice": 0.7408070775326332,
            "Hausdorff": 106.23088063270491,
            "ASSD": 3.895394629127613
        },
        "RCA score": {
            "Dice": 0.6429731589814177,
            "Hausdorff": 56.08029957123981,
            "ASSD": 4.495029343764085
        }
    },
    {
        "Real score": {
            "Dice": 0.9283171136957038,
            "Hausdorff": 107.61505470890214,
            "ASSD": 0.8793776066065218
        },
        "RCA score": {
            "Dice": 0.7040960822363246,
            "Hausdorff": 52.43090691567332,
            "ASSD": 2.381019796166205
        }
    },
    {
        "Real score": {
            "Dice": 0.9457339151425123,
            "Hausdorff": 107.61505470890214,
            "ASSD": 0.6828974599997778
        },
        "RCA score": {
            "Dice": 0.7011320173524656,
            "Hausdorff": 53.23532661682466,
            "ASSD": 2.3477827494455203
        }
    },
    {
        "Real score": {
            "Dice": 0.9577037190367764,
            "Hausdorff": 107.61505470890214,
            "ASSD": 0.4727217236091461
        },
        "RCA score": {
            "Dice": 0.715134443021767,
            "Hausdorff": 52.46903848937962,
            "ASSD": 2.1348752382256766
        }
    }
]